jsonclasses_flask/__init__.py
jsonclasses_flask/add_cors_headers.py
jsonclasses_flask/data.py
jsonclasses_flask/decode_jwt_token.py
jsonclasses_flask/empty.py
jsonclasses_flask/encode_jwt_token.py
jsonclasses_flask/ensure_operator.py
jsonclasses_flask/exception_handler.py
jsonclasses_flask/handle_cors_options.py
jsonclasses_flask/jsjson_encoder.py
jsonclasses_flask/jsonclasses_integrate.py
jsonclasses_flask/py.typed
jsonclasses_flask/remove_none.py
jsonclasses_flask/set_operator.py
jsonclasses_flask/settings.py
jsonclasses_flask-2.7.5.dist-info/LICENSE
jsonclasses_flask-2.7.5.dist-info/METADATA
jsonclasses_flask-2.7.5.dist-info/WHEEL
jsonclasses_flask-2.7.5.dist-info/top_level.txt
jsonclasses_flask-2.7.5.dist-info/RECORD
