Metadata-Version: 2.1
Name: jsonclasses-flask
Version: 2.7.5
Summary: JSONClasses integration with Flask
Home-page: https://github.com/fillmula/jsonclasses-flask
Author: Fillmula Inc.
Author-email: victor.teo@fillmula.com
License: MIT
Platform: UNKNOWN
Requires-Python: >=3.9
License-File: LICENSE
Requires-Dist: pyjwt (<3.0.0,>=2.1.0)
